imgtovar/ImgtoVar.py
imgtovar/__init__.py
imgtovar/models/Age.py
imgtovar/models/Background.py
imgtovar/models/Chart.py
imgtovar/models/Inverted.py
imgtovar/models/__init__.py
imgtovar/utils/__init__.py
imgtovar/utils/functions.py
imgtovar-1.1.5.dist-info/LICENSE.md
imgtovar-1.1.5.dist-info/METADATA
imgtovar-1.1.5.dist-info/WHEEL
imgtovar-1.1.5.dist-info/top_level.txt
imgtovar-1.1.5.dist-info/RECORD
