Metadata-Version: 2.1
Name: imgtovar
Version: 1.1.5
Summary: Extracting structured variables from image data
Home-page: https://github.com/dvdimitrov13/ImgtoVar
Author: Dimitar Dimitrov
Author-email: dvdimitrov13@gmail.com
Keywords: python,research,image data,extract variables,object detection,background detection,face detection,facial attribute analysis,chart detection,graph detection,image color analysis
Classifier: Programming Language :: Python :: 3
Classifier: License :: OSI Approved :: MIT License
Classifier: Operating System :: OS Independent
Requires-Python: >=3.7.0
License-File: LICENSE.md
Requires-Dist: tensorflow (==2.4.1)
Requires-Dist: deepface (>=0.0.75)
Requires-Dist: yolov5 (==6.1.5)
Requires-Dist: PyMuPDF (>=1.20.1)
Requires-Dist: dlib (>=19.20.0)
Requires-Dist: mediapipe (>=0.8.7.3)
